LICENSE
README.md
pyproject.toml
setup.cfg
setup.py
AnueCrawler.egg-info/PKG-INFO
AnueCrawler.egg-info/SOURCES.txt
AnueCrawler.egg-info/dependency_links.txt
AnueCrawler.egg-info/top_level.txt
anuecrawler/news/__APIBrowse.py
anuecrawler/news/__init__.py