Metadata-Version: 2.1
Name: AnueCrawler
Version: 1.0.3
Summary: Crawler for CNYes 
Home-page: https://github.com/LanDeveloper/AnueCrawler
Author: LanDeveloper
Author-email: nilm987521@gmail.com
License: UNKNOWN
Keywords: pypi,cnyes,crawler
Platform: UNKNOWN
License-File: LICENSE
